guacamole/__init__.py
guacamole/main.py
guacamole_api_wrapper-0.1.0.dist-info/LICENSE
guacamole_api_wrapper-0.1.0.dist-info/METADATA
guacamole_api_wrapper-0.1.0.dist-info/WHEEL
guacamole_api_wrapper-0.1.0.dist-info/top_level.txt
guacamole_api_wrapper-0.1.0.dist-info/RECORD
