Metadata-Version: 2.1
Name: guacamole-api-wrapper
Version: 0.1.0
Summary: A Python package that allows for simple interactions with Apache Guacamole REST API as a wrapper
Home-page: https://gitlab.com/gacybercenter/open/guacamole-api-wrapper
Author: Jonathan Race
Author-email: jrace@augusta.edu
Project-URL: Bug Tracker, https://gitlab.com/gacybercenter/open/guacamole-api-wrapper/issues
Classifier: Programming Language :: Python :: 3
Classifier: License :: OSI Approved :: Apache Software License
Classifier: Operating System :: OS Independent
Requires-Python: >=3.6
License-File: LICENSE
